commonplace/__init__.py
commonplace/__main__.py
commonplace/_config.py
commonplace/_repo.py
commonplace/_types.py
commonplace/_utils.py
commonplace/_import/__init__.py
commonplace/_import/_chatgpt.py
commonplace/_import/_claude.py
commonplace/_import/_gemini.py
commonplace/_import/_types.py
commonplace/_journal/__init__.py
commonplace/resources/gemini.txt
commonplace/resources/original-claude.txt
commonplace-0.0.3.dist-info/METADATA
commonplace-0.0.3.dist-info/WHEEL
commonplace-0.0.3.dist-info/entry_points.txt
commonplace-0.0.3.dist-info/RECORD
