Metadata-Version: 2.4
Name: commonplace
Version: 0.0.3
Summary: A personal knowledge management tool
Author-email: Joe Halliwell <joe.halliwell@gmail.com>
Requires-Python: >=3.12
Requires-Dist: beautifulsoup4>=4.13.4
Requires-Dist: html-to-markdown>=1.3.3
Requires-Dist: llm-claude>=0.4.2
Requires-Dist: llm-gemini>=0.23
Requires-Dist: llm>=0.13.0
Requires-Dist: lxml>=5.4.0
Requires-Dist: mdformat-frontmatter>=2.0.8
Requires-Dist: mdformat-gfm>=0.4.1
Requires-Dist: mdformat>=0.7.22
Requires-Dist: pydantic-settings>=2.10.0
Requires-Dist: pydantic>=2.0.0
Requires-Dist: pygit2>=1.15.0
Requires-Dist: python-dotenv>=1.0.0
Requires-Dist: python-frontmatter>=1.1.0
Requires-Dist: tqdm>=4.66.0
Requires-Dist: typer>=0.9.0
